openssh_key/__init__.py
openssh_key/__main__.py
openssh_key/key.py
openssh_key/pascal_style_byte_stream.py
openssh_key/private_key_list.py
openssh_key/utils.py
openssh_key/cipher/__init__.py
openssh_key/cipher/common.py
openssh_key/cipher/confidentiality.py
openssh_key/cipher/factory.py
openssh_key/cipher/integrity.py
openssh_key/cipher/none.py
openssh_key/kdf_options/__init__.py
openssh_key/kdf_options/bcrypt_options.py
openssh_key/kdf_options/common.py
openssh_key/kdf_options/factory.py
openssh_key/kdf_options/none.py
openssh_key/key_params/__init__.py
openssh_key/key_params/cert.py
openssh_key/key_params/common.py
openssh_key/key_params/dss.py
openssh_key/key_params/ecdsa.py
openssh_key/key_params/ed25519.py
openssh_key/key_params/factory.py
openssh_key/key_params/rsa.py
openssh_key/key_params/sk.py
tests/__init__.py
tests/test_cipher.py
tests/test_kdf.py
tests/test_key.py
tests/test_pascal_style_byte_stream.py
tests/test_private_key_list.py
tests/test_utils.py
openssh_key_parser3.8-0.0.6.2.dist-info/LICENSE
openssh_key_parser3.8-0.0.6.2.dist-info/METADATA
openssh_key_parser3.8-0.0.6.2.dist-info/WHEEL
openssh_key_parser3.8-0.0.6.2.dist-info/top_level.txt
openssh_key_parser3.8-0.0.6.2.dist-info/RECORD
