Metadata-Version: 2.1
Name: openssh-key-parser3.8
Version: 0.0.6.2
Summary: OpensshKeyParser library
Home-page: https://github.com/andreidenissov-cog/openssh_key_parser
Author: Andrei Denissov
Author-email: andrei.denissov@cognizant.com
Classifier: Programming Language :: Python :: 3
Classifier: License :: OSI Approved :: MIT License
Classifier: Operating System :: OS Independent
Requires-Python: >=3.8
License-File: LICENSE
Requires-Dist: bcrypt (>=3.0.0)
Requires-Dist: cryptography
Provides-Extra: test
Requires-Dist: pytest (>=6.0.0) ; extra == 'test'
Requires-Dist: pytest-cov ; extra == 'test'
Requires-Dist: pytest-pylint ; extra == 'test'
Requires-Dist: pytest-mock ; extra == 'test'
Requires-Dist: pytest-mypy ; extra == 'test'
Requires-Dist: pynacl ; extra == 'test'
Requires-Dist: sphinx (>=3.0.0) ; extra == 'test'
Requires-Dist: sphinx-autodoc-typehints ; extra == 'test'
